LICENSE
README.md
setup.py
pydrr/__init__.py
pydrr/bins.py
pydrr/drr3d.py
pydrr/drr3d_win.py
pydrr/drr5d.py
pydrr/genmask.py
pydrr/localfun.py
pydrr/snr.py
pydrr/utils.py
pydrr/window.py
pydrr.egg-info/PKG-INFO
pydrr.egg-info/SOURCES.txt
pydrr.egg-info/dependency_links.txt
pydrr.egg-info/not-zip-safe
pydrr.egg-info/requires.txt
pydrr.egg-info/top_level.txt
pydrr/src/calculator.c